odoo/addons/ssi_account_move_sequence/README.rst
odoo/addons/ssi_account_move_sequence/__init__.py
odoo/addons/ssi_account_move_sequence/__manifest__.py
odoo/addons/ssi_account_move_sequence/data/ir_sequence_data.xml
odoo/addons/ssi_account_move_sequence/data/sequence_template_data.xml
odoo/addons/ssi_account_move_sequence/models/__init__.py
odoo/addons/ssi_account_move_sequence/models/account_journal.py
odoo/addons/ssi_account_move_sequence/models/account_move.py
odoo/addons/ssi_account_move_sequence/static/description/icon.png
odoo/addons/ssi_account_move_sequence/views/account_journal_views.xml
odoo14_addon_ssi_account_move_sequence-14.0.1.2.2.dev1.dist-info/METADATA
odoo14_addon_ssi_account_move_sequence-14.0.1.2.2.dev1.dist-info/WHEEL
odoo14_addon_ssi_account_move_sequence-14.0.1.2.2.dev1.dist-info/top_level.txt
odoo14_addon_ssi_account_move_sequence-14.0.1.2.2.dev1.dist-info/RECORD
